<?xml version="1.0" encoding="UTF-8"?>
<computer_extension_attribute>
  <name>Last System Boot</name>
  <enabled>true</enabled>
  <description>Extension attribute that will display the date (YYYY-MM-DD HH:MM:SS) the computer was booted up. If no time can be detected, output will be: "Unknown"</description>
  <data_type>Date</data_type>
  <input_type>
    <type>script</type>
    <platform>Mac</platform>
  </input_type>
  <inventory_display>General</inventory_display>
</computer_extension_attribute>
